pycutroh/__init__.py
pycutroh/__main__.py
pycutroh-0.1.2.dist-info/LICENSE
pycutroh-0.1.2.dist-info/METADATA
pycutroh-0.1.2.dist-info/WHEEL
pycutroh-0.1.2.dist-info/top_level.txt
pycutroh-0.1.2.dist-info/RECORD
