Metadata-Version: 2.1
Name: pycutroh
Version: 0.1.2
Summary: A python module for cutting strings.
Author: IT-Administrators
Maintainer: IT-Administrators
License: MIT License
Project-URL: Homepage, https://github.com/IT-Administrators/pycutroh
Keywords: string,cut
Classifier: Programming Language :: Python :: 3
Classifier: License :: OSI Approved :: MIT License
Classifier: Operating System :: OS Independent
Requires-Python: >=3.7
License-File: LICENSE
